{
    "version": 1,
    "var_self": {
        "type": "TRANSFORM",
        "id": "0a3494fa-cadd-4e82-96bb-1274f2384e8a",
        "name": "Division"
    },
    "object": {
        "id": "0a3494fa-cadd-4e82-96bb-1274f2384e8a",
        "name": "Division",
        "type": "static",
        "attributes": {
            "TransformDesrcription": {
                "type": "static",
                "value": "Division value from SF - New as of 2025-04-16"
            },
            "exceptionText": {
                "type": "static",
                "value": "error:undetermined:transform:Division"
            },
            "bestSource": {
                "type": "reference",
                "attributes": {
                    "id": "BestSource"
                }
            },
            "SFAuth_value": {
                "type": "firstValid",
                "attributes": {
                    "values": [
                        {
                            "type": "accountAttribute",
                            "attributes": {
                                "sourceName": "SuccessFactors-Auth",
                                "attributeName": "Division",
                                "accountSortAttribute": "StartDate_EmpInfo",
                                "accountSortDescending": true,
                                "accountReturnFirstLink": true
                            }
                        },
                        "null"
                    ]
                }
            },
            "SFNonAuth_value": {
                "type": "firstValid",
                "attributes": {
                    "values": [
                        {
                            "type": "accountAttribute",
                            "attributes": {
                                "sourceName": "SuccessFactors - NonAuthoritative",
                                "attributeName": "Division",
                                "accountSortAttribute": "StartDate_EmpInfo",
                                "accountSortDescending": true,
                                "accountReturnFirstLink": true
                            }
                        },
                        "null"
                    ]
                }
            },
            "SAP_value": {
                "type": "firstValid",
                "attributes": {
                    "values": [
                        "null",
                        "There is no SAPECC  <Division> attribute."
                    ]
                }
            },
            "SIS_value": {
                "type": "firstValid",
                "attributes": {
                    "values": [
                        "null",
                        "There is no Advisors - SIS Feed <Division> attribute."
                    ]
                }
            },
            "SNOW_value": {
                "type": "firstValid",
                "attributes": {
                    "values": [
                        "null",
                        "There is no ServiceNowAPI <Division> attribute."
                    ]
                }
            },
            "value": "#if($bestSource == 'use_SFAuth')#set($finalValue = $SFAuth_value)#elseif($bestSource == 'use_SFNonAuth')#set($finalValue = $SFNonAuth_value)#elseif($bestSource == 'use_SAPECC')#set($finalValue = $SAP_value)#elseif($bestSource == 'use_SIS')#set($finalValue = $SIS_value)#elseif($bestSource.compareToIgnoreCase('use_servicenow') == 0)#set($finalValue = $SNOW_value)#{else}#set($finalValue = $exceptionText)#end#if($finalValue != 'null')$finalValue#end"
        },
        "internal": false
    }
}