{
    "version": 1,
    "var_self": {
        "type": "TRANSFORM",
        "id": "c657e0e9-7f32-45f1-bcb3-28f93289462b",
        "name": "LifecycleState"
    },
    "object": {
        "id": "c657e0e9-7f32-45f1-bcb3-28f93289462b",
        "name": "LifecycleState",
        "type": "static",
        "attributes": {
            "requiresPeriodicRefresh": true,
            "lcsActiveCheck": {
                "type": "reference",
                "attributes": {
                    "id": "LCSActiveCheck"
                }
            },
            "lcsDeleteCheck": {
                "type": "reference",
                "attributes": {
                    "id": "LCSDeleteCheck"
                }
            },
            "lcsLoaCheck": {
                "type": "reference",
                "attributes": {
                    "id": "LCSLoaCheck"
                }
            },
            "lcsPrehireCheck": {
                "type": "reference",
                "attributes": {
                    "id": "LCSPrehireCheck"
                }
            },
            "lcsTerminationCheck": {
                "type": "reference",
                "attributes": {
                    "id": "LCSTerminatedCheck"
                }
            },
            "value": "#if($lcsActiveCheck == 'true')active#elseif($lcsDeleteCheck == 'true')deleted#elseif($lcsLoaCheck == 'true')suspended#elseif($lcsPrehireCheck == 'true')prehire#elseif($lcsTerminationCheck == 'true')terminated#{else}undefined#end"
        },
        "internal": false
    }
}