{
    "version": 1,
    "var_self": {
        "type": "TRANSFORM",
        "id": "a7bc37ab-1099-4e6c-b592-b19080995337",
        "name": "RepRelationships"
    },
    "object": {
        "id": "a7bc37ab-1099-4e6c-b592-b19080995337",
        "name": "RepRelationships",
        "type": "static",
        "attributes": {
            "TransformDesrcription": {
                "type": "static",
                "attributes": {
                    "Comment_20250715": "Scott Walker - Initial version. Previously could just use the source attribute directly.",
                    "value": "Used to Populate repRelationships identity attribute. This indicates the AdvisorIDs of persons supported by the given assistant or associate person."
                }
            },
            "exceptionText": {
                "type": "static",
                "attributes": {
                    "value": "transform:RepRelaionships:unhandled_case"
                }
            },
            "bestSource": {
                "type": "reference",
                "attributes": {
                    "id": "BestSource"
                }
            },
            "SFAuth_value": {
                "type": "firstValid",
                "attributes": {
                    "values": [
                        {
                            "type": "accountAttribute",
                            "attributes": {
                                "sourceName": "SF Extra Attr",
                                "attributeName": "repRelationships"
                            }
                        },
                        "null"
                    ]
                }
            },
            "SFNonAuth_value": {
                "type": "firstValid",
                "attributes": {
                    "values": [
                        {
                            "type": "accountAttribute",
                            "attributes": {
                                "sourceName": "SF Extra Attr",
                                "attributeName": "repRelationships"
                            }
                        },
                        "null"
                    ]
                }
            },
            "SAP_value": {
                "type": "static",
                "attributes": {
                    "value": "null"
                }
            },
            "SIS_value": {
                "type": "firstValid",
                "attributes": {
                    "values": [
                        {
                            "type": "accountAttribute",
                            "attributes": {
                                "sourceName": "Advisors - SIS Feed",
                                "attributeName": "REP-RELATIONSHIPS"
                            }
                        },
                        "null"
                    ]
                }
            },
            "SNOW_value": {
                "type": "static",
                "attributes": {
                    "value": "null"
                }
            },
            "value": "#if($bestSource == 'use_SFAuth')#set($finalValue = $SFAuth_value)#elseif($bestSource == 'use_SFNonAuth')#set($finalValue = $SFNonAuth_value)#elseif($bestSource == 'use_SAPECC')#set($finalValue = $SAP_value)#elseif($bestSource == 'use_SIS')#set($finalValue = $SIS_value)#elseif($bestSource.compareToIgnoreCase('use_servicenow') == 0)#set($finalValue = $SNOW_value)#{else}#set($finalValue = $exceptionText)#end#if($finalValue != 'null')$finalValue#end"
        },
        "internal": false
    }
}